Metadata-Version: 2.1
Name: topsis-10191117pip-yash
Version: 1.0.0
Summary: A Python package implementing TOPSIS technique.
Home-page: UNKNOWN
Author: Yashwardhan Rathore
Author-email: yrathore_be19@thapar.edu
License: MIT
Platform: UNKNOWN
Classifier: License :: OSI Approved :: MIT License
Classifier: Programming Language :: Python :: 3
Classifier: Programming Language :: Python :: 3.9
Requires-Dist: scipy
Requires-Dist: tabulate
Requires-Dist: numpy
Requires-Dist: pandas
